{
  "folds": [
    {
      "fold": 0,
      "log_loss": 1.0279414541682892,
      "n_val": 11496
    },
    {
      "fold": 1,
      "log_loss": 1.0337852481243661,
      "n_val": 11496
    },
    {
      "fold": 2,
      "log_loss": 1.0212118087977067,
      "n_val": 11495
    },
    {
      "fold": 3,
      "log_loss": 1.0297270858568786,
      "n_val": 11495
    },
    {
      "fold": 4,
      "log_loss": 1.0285832844480753,
      "n_val": 11495
    }
  ],
  "overall_oof_log_loss": 1.0282498672223923
}